odoo8_addon_contract_show_invoice-8.0.2.1.0-py2.7-nspkg.pth
odoo_addons/contract_show_invoice/__openerp__.py
odoo_addons/contract_show_invoice/__init__.py
odoo_addons/contract_show_invoice/README.rst
odoo_addons/contract_show_invoice/i18n/es.po
odoo_addons/contract_show_invoice/i18n/sl.po
odoo_addons/contract_show_invoice/i18n/contract_invoices_button.pot
odoo_addons/contract_show_invoice/i18n/sk_SK.po
odoo_addons/contract_show_invoice/i18n/de.po
odoo_addons/contract_show_invoice/i18n/fr.po
odoo_addons/contract_show_invoice/i18n/pt_BR.po
odoo_addons/contract_show_invoice/i18n/fi.po
odoo_addons/contract_show_invoice/views/contract_view.xml
odoo8_addon_contract_show_invoice-8.0.2.1.0.dist-info/top_level.txt
odoo8_addon_contract_show_invoice-8.0.2.1.0.dist-info/WHEEL
odoo8_addon_contract_show_invoice-8.0.2.1.0.dist-info/RECORD
odoo8_addon_contract_show_invoice-8.0.2.1.0.dist-info/metadata.json
odoo8_addon_contract_show_invoice-8.0.2.1.0.dist-info/DESCRIPTION.rst
odoo8_addon_contract_show_invoice-8.0.2.1.0.dist-info/METADATA
odoo8_addon_contract_show_invoice-8.0.2.1.0.dist-info/namespace_packages.txt
