Metadata-Version: 2.0
Name: odoo8-addon-contract-show-invoice
Version: 8.0.2.1.0
Summary: Button in contracts to show their invoices
Home-page: http://www.domatix.com
Author: UNKNOWN
Author-email: UNKNOWN
License: UNKNOWN
Platform: UNKNOWN
Requires-Dist: odoo (<9.0a,>=8.0a)
Classifier: Programming Language :: Python :: 2.7
Classifier: Framework :: Odoo
